GPro/__init__.py
GPro/acquisitions.py
GPro/del.py
GPro/kernels.py
GPro/optimization.py
GPro/posterior.py
GPro/preference.py
GPro/validations.py
GPro-1.0.5.dist-info/LICENSE
GPro-1.0.5.dist-info/METADATA
GPro-1.0.5.dist-info/WHEEL
GPro-1.0.5.dist-info/top_level.txt
GPro-1.0.5.dist-info/RECORD
